manuelharofulgencio5/__init__.py
manuelharofulgencio5/opengate_client.py
manuelharofulgencio5/ai_models/__init__.py
manuelharofulgencio5/ai_models/ai_models.py
manuelharofulgencio5/ai_pipelines/__init__.py
manuelharofulgencio5/ai_pipelines/ai_pipelines.py
manuelharofulgencio5/ai_transformers/__init__.py
manuelharofulgencio5/ai_transformers/ai_transformers.py
manuelharofulgencio5/datapoints/__init__.py
manuelharofulgencio5/datapoints/datapoints.py
manuelharofulgencio5/datasets/__init__.py
manuelharofulgencio5/datasets/datasets.py
manuelharofulgencio5/entities/__init__.py
manuelharofulgencio5/entities/entities.py
manuelharofulgencio5/rules/__init__.py
manuelharofulgencio5/rules/rules.py
manuelharofulgencio5/test/__init__.py
manuelharofulgencio5/test/ownworld.py
manuelharofulgencio5/test/test_steps_cucumber.py
manuelharofulgencio5/timeseries/__init__.py
manuelharofulgencio5/timeseries/timeseries.py
manuelharofulgencio5-1.0.0.dist-info/METADATA
manuelharofulgencio5-1.0.0.dist-info/WHEEL
manuelharofulgencio5-1.0.0.dist-info/top_level.txt
manuelharofulgencio5-1.0.0.dist-info/RECORD
